uncertainty_engine/__init__.py
uncertainty_engine/api_invoker.py
uncertainty_engine/api_providers/__init__.py
uncertainty_engine/api_providers/api_provider.py
uncertainty_engine/api_providers/auth_provider.py
uncertainty_engine/api_providers/constants.py
uncertainty_engine/api_providers/models.py
uncertainty_engine/api_providers/projects_provider.py
uncertainty_engine/api_providers/resource_provider.py
uncertainty_engine/api_providers/workflows_provider.py
uncertainty_engine/auth_service.py
uncertainty_engine/client.py
uncertainty_engine/cognito_authenticator.py
uncertainty_engine/environments/__init__.py
uncertainty_engine/environments/dev.json
uncertainty_engine/environments/environment.py
uncertainty_engine/environments/local.json
uncertainty_engine/environments/prod.json
uncertainty_engine/exceptions/__init__.py
uncertainty_engine/exceptions/incomplete_credentials.py
uncertainty_engine/exceptions/py.typed
uncertainty_engine/graph.py
uncertainty_engine/nodes/__init__.py
uncertainty_engine/nodes/base.py
uncertainty_engine/nodes/basic.py
uncertainty_engine/nodes/sensor_designer.py
uncertainty_engine/nodes/workflow.py
uncertainty_engine/types.py
uncertainty_engine/uri.py
uncertainty_engine/utils.py
uncertainty_engine/visualization.py
uncertainty_engine-0.10.0.dist-info/METADATA
uncertainty_engine-0.10.0.dist-info/WHEEL
uncertainty_engine-0.10.0.dist-info/RECORD
