Metadata-Version: 2.3
Name: uncertainty-engine
Version: 0.10.0
Summary: SDK for the Uncertainty Engine
Author: digiLab Solutions Ltd.
Author-email: info@digilab.ai
Maintainer: Jamie Donald-McCann
Maintainer-email: jamie.donald-mccann@digilab.ai
Requires-Python: >=3.10,<3.14
Classifier: Programming Language :: Python :: 3
Classifier: Programming Language :: Python :: 3.10
Classifier: Programming Language :: Python :: 3.11
Classifier: Programming Language :: Python :: 3.12
Classifier: Programming Language :: Python :: 3.13
Provides-Extra: data
Provides-Extra: notebook
Provides-Extra: vis
Requires-Dist: boto3 (>=1.38.14,<2.0.0)
Requires-Dist: boto3-stubs[cognito-idp] (>=1.38.20,<2.0.0)
Requires-Dist: botocore (>=1.38.14,<2.0.0)
Requires-Dist: ipykernel (>=6.29.5,<7.0.0) ; extra == "notebook"
Requires-Dist: matplotlib (>=3.10.0,<4.0.0) ; extra == "vis"
Requires-Dist: networkx (>=3.4.2,<4.0.0) ; extra == "vis"
Requires-Dist: numpy (>=2.2.6,<3.0.0) ; extra == "data"
Requires-Dist: pandas (>=2.2.3,<3.0.0) ; extra == "data"
Requires-Dist: pyjwt (>=2.10.1,<3.0.0)
Requires-Dist: requests (>=2.32.4,<3.0.0)
Requires-Dist: typeguard (>=4.4.2,<5.0.0)
Requires-Dist: uncertainty-engine-resource-client (>=0.1.0,<0.2.0)
Requires-Dist: uncertainty-engine-types (>=0.7.0,<0.8.0)
